README
setup.py
examples/__init__.py
mcviz/__init__.py
mcviz/exception.py
mcviz/help.py
mcviz/logger.py
mcviz/main.py
mcviz/options.py
mcviz/workspace.py
mcviz.egg-info/PKG-INFO
mcviz.egg-info/SOURCES.txt
mcviz.egg-info/dependency_links.txt
mcviz.egg-info/entry_points.txt
mcviz.egg-info/requires.txt
mcviz.egg-info/top_level.txt
mcviz/graph/__init__.py
mcviz/graph/graph.py
mcviz/graph/particle.py
mcviz/graph/vertex.py
mcviz/graph/view.py
mcviz/graph/view_object.py
mcviz/graph/view_particle.py
mcviz/graph/view_vertex.py
mcviz/graph/walk.py
mcviz/graph/loaders/__init__.py
mcviz/graph/loaders/hepmc.py
mcviz/graph/loaders/leshouchesevent.py
mcviz/graph/loaders/pythialog.py
mcviz/tests/__init__.py
mcviz/tests/test_graph.py
mcviz/tests/test_particle_names.py
mcviz/tools/__init__.py
mcviz/tools/tools.py
mcviz/tools/types.py
mcviz/tools/annotations/__init__.py
mcviz/tools/annotations/annotations.py
mcviz/tools/layout_engines/__init__.py
mcviz/tools/layout_engines/graphviz.py
mcviz/tools/layouts/__init__.py
mcviz/tools/layouts/circle.py
mcviz/tools/layouts/dual.py
mcviz/tools/layouts/extra.py
mcviz/tools/layouts/feynman.py
mcviz/tools/layouts/layouts.py
mcviz/tools/layouts/phi.py
mcviz/tools/optionsets/__init__.py
mcviz/tools/optionsets/optionsets.py
mcviz/tools/painters/__init__.py
mcviz/tools/painters/painters.py
mcviz/tools/painters/svg.py
mcviz/tools/styles/__init__.py
mcviz/tools/styles/qcd.py
mcviz/tools/styles/styles.py
mcviz/tools/transforms/__init__.py
mcviz/tools/transforms/selections.py
mcviz/tools/transforms/tagging.py
mcviz/tools/transforms/transforms.py
mcviz/utils/__init__.py
mcviz/utils/colors.py
mcviz/utils/demo.py
mcviz/utils/graphviz.py
mcviz/utils/make_bootstrap.py
mcviz/utils/nanodom.py
mcviz/utils/orderedset.py
mcviz/utils/point.py
mcviz/utils/spline.py
mcviz/utils/timer.py
mcviz/utils/trydecompress.py
mcviz/utils/units.py
mcviz/utils/svg/__init__.py
mcviz/utils/svg/feynman_shapes.py
mcviz/utils/svg/svg_document.py
mcviz/utils/svg/texglyph.py
mcviz/utils/svg/data/ParticleData.xml
mcviz/utils/svg/data/__init__.py
mcviz/utils/svg/data/jquery.js
mcviz/utils/svg/data/jquery.svg.js
mcviz/utils/svg/data/jquery.svgdom.js
